{
  "code": "slider",
  "name": "Bozkurt Premium Slider",
  "version": "1.1.0",
  "description": "Tema kancası üzerinden ana sayfa slider gösterimi sağlar.",
  "author": "Bozkurt Core Team",
  "type": "module",
  "entry": "init.php",
  "settings_schema": [
    {
      "key": "otomatik_akisma",
      "label": "Otomatik Geçiş",
      "type": "bool",
      "default": "1"
    },
    {
      "key": "gecis_suresi_ms",
      "label": "Geçiş Süresi (ms)",
      "type": "int",
      "default": 5000
    }
  ]
}
